odoo10_addon_l10n_be_antibiotic_tax-10.0.1.0.0.99.dev7-py2.7-nspkg.pth
odoo/addons/l10n_be_antibiotic_tax/README.rst
odoo/addons/l10n_be_antibiotic_tax/__init__.py
odoo/addons/l10n_be_antibiotic_tax/__manifest__.py
odoo/addons/l10n_be_antibiotic_tax/data/account_account_template_data.xml
odoo/addons/l10n_be_antibiotic_tax/data/account_tax_code_template.xml
odoo/addons/l10n_be_antibiotic_tax/data/account_tax_template_antibiotic_in_data.xml
odoo/addons/l10n_be_antibiotic_tax/data/account_tax_template_antibiotic_out_data.xml
odoo/addons/l10n_be_antibiotic_tax/i18n/l10n_be_antibiotic_tax.pot
odoo/addons/l10n_be_antibiotic_tax/static/description/icon.png
odoo10_addon_l10n_be_antibiotic_tax-10.0.1.0.0.99.dev7.dist-info/METADATA
odoo10_addon_l10n_be_antibiotic_tax-10.0.1.0.0.99.dev7.dist-info/RECORD
odoo10_addon_l10n_be_antibiotic_tax-10.0.1.0.0.99.dev7.dist-info/WHEEL
odoo10_addon_l10n_be_antibiotic_tax-10.0.1.0.0.99.dev7.dist-info/namespace_packages.txt
odoo10_addon_l10n_be_antibiotic_tax-10.0.1.0.0.99.dev7.dist-info/top_level.txt
